clk_div.v
module clk_div (
    input clk,
    output reg [3:0] count
);

integer i;
reg clkdiv;

initial begin
    i = 0;
    count = 4'b0000;
    clkdiv = 1'b0;
end

always @(posedge clk) begin
    i = i+1;
    if (i == 4) begin
        clkdiv = ~clkdiv;
        i = 0;
    end
end

always @(posedge clkdiv) begin
    count = count+1;
end

endmodule

testbench.v
module testbench;

    reg clk;
    wire [3:0] count;

    clk_div dut(.clk(clk),.count(count));

    always #1 clk = ~clk;

    initial begin
        $dumpfile("testbench.vcd");
        $dumpvars(0,testbench);
        clk <= 1'b0;
        $monitor("clk = %d , count = %d\n",clk,count);
    end

    initial #1000 $finish;

endmodule

testbench.vcd
$date
	Sat Sep 16 10:33:03 2023
$end
$version
	Icarus Verilog
$end
$timescale
	1s
$end
$scope module testbench $end
$var wire 4 ! count [3:0] $end
$var reg 1 " clk $end
$scope module dut $end
$var wire 1 " clk $end
$var reg 1 # clkdiv $end
$var reg 4 $ count [3:0] $end
$var integer 32 % i [31:0] $end
$upscope $end
$upscope $end
$enddefinitions $end
$comment Show the parameter values. $end
$dumpall
$end
#0
$dumpvars
b0 %
b0 $
0#
0"
b0 !
$end
#1
b1 %
1"
#2
0"
#3
b10 %
1"
#4
0"
#5
b11 %
1"
#6
0"
#7
b1 !
b1 $
1#
b0 %
1"
#8
0"
#9
b1 %
1"
#10
0"
#11
b10 %
1"
#12
0"
#13
b11 %
1"
#14
0"
#15
0#
b0 %
1"
#16
0"
#17
b1 %
1"
#18
0"
#19
b10 %
1"
#20
0"
#21
b11 %
1"
#22
0"
#23
b10 !
b10 $
1#
b0 %
1"
#24
0"
#25
b1 %
1"
#26
0"
#27
b10 %
1"
#28
0"
#29
b11 %
1"
#30
0"
#31
0#
b0 %
1"
#32
0"
#33
b1 %
1"
#34
0"
#35
b10 %
1"
#36
0"
#37
b11 %
1"
#38
0"
#39
b11 !
b11 $
1#
b0 %
1"
#40
0"
#41
b1 %
1"
#42
0"
#43
b10 %
1"
#44
0"
#45
b11 %
1"
#46
0"
#47
0#
b0 %
1"
#48
0"
#49
b1 %
1"
#50
0"
#51
b10 %
1"
#52
0"
#53
b11 %
1"
#54
0"
#55
b100 !
b100 $
1#
b0 %
1"
#56
0"
#57
b1 %
1"
#58
0"
#59
b10 %
1"
#60
0"
#61
b11 %
1"
#62
0"
#63
0#
b0 %
1"
#64
0"
#65
b1 %
1"
#66
0"
#67
b10 %
1"
#68
0"
#69
b11 %
1"
#70
0"
#71
b101 !
b101 $
1#
b0 %
1"
#72
0"
#73
b1 %
1"
#74
0"
#75
b10 %
1"
#76
0"
#77
b11 %
1"
#78
0"
#79
0#
b0 %
1"
#80
0"
#81
b1 %
1"
#82
0"
#83
b10 %
1"
#84
0"
#85
b11 %
1"
#86
0"
#87
b110 !
b110 $
1#
b0 %
1"
#88
0"
#89
b1 %
1"
#90
0"
#91
b10 %
1"
#92
0"
#93
b11 %
1"
#94
0"
#95
0#
b0 %
1"
#96
0"
#97
b1 %
1"
#98
0"
#99
b10 %
1"
#100
0"
#101
b11 %
1"
#102
0"
#103
b111 !
b111 $
1#
b0 %
1"
#104
0"
#105
b1 %
1"
#106
0"
#107
b10 %
1"
#108
0"
#109
b11 %
1"
#110
0"
#111
0#
b0 %
1"
#112
0"
#113
b1 %
1"
#114
0"
#115
b10 %
1"
#116
0"
#117
b11 %
1"
#118
0"
#119
b1000 !
b1000 $
1#
b0 %
1"
#120
0"
#121
b1 %
1"
#122
0"
#123
b10 %
1"
#124
0"
#125
b11 %
1"
#126
0"
#127
0#
b0 %
1"
#128
0"
#129
b1 %
1"
#130
0"
#131
b10 %
1"
#132
0"
#133
b11 %
1"
#134
0"
#135
b1001 !
b1001 $
1#
b0 %
1"
#136
0"
#137
b1 %
1"
#138
0"
#139
b10 %
1"
#140
0"
#141
b11 %
1"
#142
0"
#143
0#
b0 %
1"
#144
0"
#145
b1 %
1"
#146
0"
#147
b10 %
1"
#148
0"
#149
b11 %
1"
#150
0"
#151
b1010 !
b1010 $
1#
b0 %
1"
#152
0"
#153
b1 %
1"
#154
0"
#155
b10 %
1"
#156
0"
#157
b11 %
1"
#158
0"
#159
0#
b0 %
1"
#160
0"
#161
b1 %
1"
#162
0"
#163
b10 %
1"
#164
0"
#165
b11 %
1"
#166
0"
#167
b1011 !
b1011 $
1#
b0 %
1"
#168
0"
#169
b1 %
1"
#170
0"
#171
b10 %
1"
#172
0"
#173
b11 %
1"
#174
0"
#175
0#
b0 %
1"
#176
0"
#177
b1 %
1"
#178
0"
#179
b10 %
1"
#180
0"
#181
b11 %
1"
#182
0"
#183
b1100 !
b1100 $
1#
b0 %
1"
#184
0"
#185
b1 %
1"
#186
0"
#187
b10 %
1"
#188
0"
#189
b11 %
1"
#190
0"
#191
0#
b0 %
1"
#192
0"
#193
b1 %
1"
#194
0"
#195
b10 %
1"
#196
0"
#197
b11 %
1"
#198
0"
#199
b1101 !
b1101 $
1#
b0 %
1"
#200
0"
#201
b1 %
1"
#202
0"
#203
b10 %
1"
#204
0"
#205
b11 %
1"
#206
0"
#207
0#
b0 %
1"
#208
0"
#209
b1 %
1"
#210
0"
#211
b10 %
1"
#212
0"
#213
b11 %
1"
#214
0"
#215
b1110 !
b1110 $
1#
b0 %
1"
#216
0"
#217
b1 %
1"
#218
0"
#219
b10 %
1"
#220
0"
#221
b11 %
1"
#222
0"
#223
0#
b0 %
1"
#224
0"
#225
b1 %
1"
#226
0"
#227
b10 %
1"
#228
0"
#229
b11 %
1"
#230
0"
#231
b1111 !
b1111 $
1#
b0 %
1"
#232
0"
#233
b1 %
1"
#234
0"
#235
b10 %
1"
#236
0"
#237
b11 %
1"
#238
0"
#239
0#
b0 %
1"
#240
0"
#241
b1 %
1"
#242
0"
#243
b10 %
1"
#244
0"
#245
b11 %
1"
#246
0"
#247
b0 !
b0 $
1#
b0 %
1"
#248
0"
#249
b1 %
1"
#250
0"
#251
b10 %
1"
#252
0"
#253
b11 %
1"
#254
0"
#255
0#
b0 %
1"
#256
0"
#257
b1 %
1"
#258
0"
#259
b10 %
1"
#260
0"
#261
b11 %
1"
#262
0"
#263
b1 !
b1 $
1#
b0 %
1"
#264
0"
#265
b1 %
1"
#266
0"
#267
b10 %
1"
#268
0"
#269
b11 %
1"
#270
0"
#271
0#
b0 %
1"
#272
0"
#273
b1 %
1"
#274
0"
#275
b10 %
1"
#276
0"
#277
b11 %
1"
#278
0"
#279
b10 !
b10 $
1#
b0 %
1"
#280
0"
#281
b1 %
1"
#282
0"
#283
b10 %
1"
#284
0"
#285
b11 %
1"
#286
0"
#287
0#
b0 %
1"
#288
0"
#289
b1 %
1"
#290
0"
#291
b10 %
1"
#292
0"
#293
b11 %
1"
#294
0"
#295
b11 !
b11 $
1#
b0 %
1"
#296
0"
#297
b1 %
1"
#298
0"
#299
b10 %
1"
#300
0"
#301
b11 %
1"
#302
0"
#303
0#
b0 %
1"
#304
0"
#305
b1 %
1"
#306
0"
#307
b10 %
1"
#308
0"
#309
b11 %
1"
#310
0"
#311
b100 !
b100 $
1#
b0 %
1"
#312
0"
#313
b1 %
1"
#314
0"
#315
b10 %
1"
#316
0"
#317
b11 %
1"
#318
0"
#319
0#
b0 %
1"
#320
0"
#321
b1 %
1"
#322
0"
#323
b10 %
1"
#324
0"
#325
b11 %
1"
#326
0"
#327
b101 !
b101 $
1#
b0 %
1"
#328
0"
#329
b1 %
1"
#330
0"
#331
b10 %
1"
#332
0"
#333
b11 %
1"
#334
0"
#335
0#
b0 %
1"
#336
0"
#337
b1 %
1"
#338
0"
#339
b10 %
1"
#340
0"
#341
b11 %
1"
#342
0"
#343
b110 !
b110 $
1#
b0 %
1"
#344
0"
#345
b1 %
1"
#346
0"
#347
b10 %
1"
#348
0"
#349
b11 %
1"
#350
0"
#351
0#
b0 %
1"
#352
0"
#353
b1 %
1"
#354
0"
#355
b10 %
1"
#356
0"
#357
b11 %
1"
#358
0"
#359
b111 !
b111 $
1#
b0 %
1"
#360
0"
#361
b1 %
1"
#362
0"
#363
b10 %
1"
#364
0"
#365
b11 %
1"
#366
0"
#367
0#
b0 %
1"
#368
0"
#369
b1 %
1"
#370
0"
#371
b10 %
1"
#372
0"
#373
b11 %
1"
#374
0"
#375
b1000 !
b1000 $
1#
b0 %
1"
#376
0"
#377
b1 %
1"
#378
0"
#379
b10 %
1"
#380
0"
#381
b11 %
1"
#382
0"
#383
0#
b0 %
1"
#384
0"
#385
b1 %
1"
#386
0"
#387
b10 %
1"
#388
0"
#389
b11 %
1"
#390
0"
#391
b1001 !
b1001 $
1#
b0 %
1"
#392
0"
#393
b1 %
1"
#394
0"
#395
b10 %
1"
#396
0"
#397
b11 %
1"
#398
0"
#399
0#
b0 %
1"
#400
0"
#401
b1 %
1"
#402
0"
#403
b10 %
1"
#404
0"
#405
b11 %
1"
#406
0"
#407
b1010 !
b1010 $
1#
b0 %
1"
#408
0"
#409
b1 %
1"
#410
0"
#411
b10 %
1"
#412
0"
#413
b11 %
1"
#414
0"
#415
0#
b0 %
1"
#416
0"
#417
b1 %
1"
#418
0"
#419
b10 %
1"
#420
0"
#421
b11 %
1"
#422
0"
#423
b1011 !
b1011 $
1#
b0 %
1"
#424
0"
#425
b1 %
1"
#426
0"
#427
b10 %
1"
#428
0"
#429
b11 %
1"
#430
0"
#431
0#
b0 %
1"
#432
0"
#433
b1 %
1"
#434
0"
#435
b10 %
1"
#436
0"
#437
b11 %
1"
#438
0"
#439
b1100 !
b1100 $
1#
b0 %
1"
#440
0"
#441
b1 %
1"
#442
0"
#443
b10 %
1"
#444
0"
#445
b11 %
1"
#446
0"
#447
0#
b0 %
1"
#448
0"
#449
b1 %
1"
#450
0"
#451
b10 %
1"
#452
0"
#453
b11 %
1"
#454
0"
#455
b1101 !
b1101 $
1#
b0 %
1"
#456
0"
#457
b1 %
1"
#458
0"
#459
b10 %
1"
#460
0"
#461
b11 %
1"
#462
0"
#463
0#
b0 %
1"
#464
0"
#465
b1 %
1"
#466
0"
#467
b10 %
1"
#468
0"
#469
b11 %
1"
#470
0"
#471
b1110 !
b1110 $
1#
b0 %
1"
#472
0"
#473
b1 %
1"
#474
0"
#475
b10 %
1"
#476
0"
#477
b11 %
1"
#478
0"
#479
0#
b0 %
1"
#480
0"
#481
b1 %
1"
#482
0"
#483
b10 %
1"
#484
0"
#485
b11 %
1"
#486
0"
#487
b1111 !
b1111 $
1#
b0 %
1"
#488
0"
#489
b1 %
1"
#490
0"
#491
b10 %
1"
#492
0"
#493
b11 %
1"
#494
0"
#495
0#
b0 %
1"
#496
0"
#497
b1 %
1"
#498
0"
#499
b10 %
1"
#500
0"
#501
b11 %
1"
#502
0"
#503
b0 !
b0 $
1#
b0 %
1"
#504
0"
#505
b1 %
1"
#506
0"
#507
b10 %
1"
#508
0"
#509
b11 %
1"
#510
0"
#511
0#
b0 %
1"
#512
0"
#513
b1 %
1"
#514
0"
#515
b10 %
1"
#516
0"
#517
b11 %
1"
#518
0"
#519
b1 !
b1 $
1#
b0 %
1"
#520
0"
#521
b1 %
1"
#522
0"
#523
b10 %
1"
#524
0"
#525
b11 %
1"
#526
0"
#527
0#
b0 %
1"
#528
0"
#529
b1 %
1"
#530
0"
#531
b10 %
1"
#532
0"
#533
b11 %
1"
#534
0"
#535
b10 !
b10 $
1#
b0 %
1"
#536
0"
#537
b1 %
1"
#538
0"
#539
b10 %
1"
#540
0"
#541
b11 %
1"
#542
0"
#543
0#
b0 %
1"
#544
0"
#545
b1 %
1"
#546
0"
#547
b10 %
1"
#548
0"
#549
b11 %
1"
#550
0"
#551
b11 !
b11 $
1#
b0 %
1"
#552
0"
#553
b1 %
1"
#554
0"
#555
b10 %
1"
#556
0"
#557
b11 %
1"
#558
0"
#559
0#
b0 %
1"
#560
0"
#561
b1 %
1"
#562
0"
#563
b10 %
1"
#564
0"
#565
b11 %
1"
#566
0"
#567
b100 !
b100 $
1#
b0 %
1"
#568
0"
#569
b1 %
1"
#570
0"
#571
b10 %
1"
#572
0"
#573
b11 %
1"
#574
0"
#575
0#
b0 %
1"
#576
0"
#577
b1 %
1"
#578
0"
#579
b10 %
1"
#580
0"
#581
b11 %
1"
#582
0"
#583
b101 !
b101 $
1#
b0 %
1"
#584
0"
#585
b1 %
1"
#586
0"
#587
b10 %
1"
#588
0"
#589
b11 %
1"
#590
0"
#591
0#
b0 %
1"
#592
0"
#593
b1 %
1"
#594
0"
#595
b10 %
1"
#596
0"
#597
b11 %
1"
#598
0"
#599
b110 !
b110 $
1#
b0 %
1"
#600
0"
#601
b1 %
1"
#602
0"
#603
b10 %
1"
#604
0"
#605
b11 %
1"
#606
0"
#607
0#
b0 %
1"
#608
0"
#609
b1 %
1"
#610
0"
#611
b10 %
1"
#612
0"
#613
b11 %
1"
#614
0"
#615
b111 !
b111 $
1#
b0 %
1"
#616
0"
#617
b1 %
1"
#618
0"
#619
b10 %
1"
#620
0"
#621
b11 %
1"
#622
0"
#623
0#
b0 %
1"
#624
0"
#625
b1 %
1"
#626
0"
#627
b10 %
1"
#628
0"
#629
b11 %
1"
#630
0"
#631
b1000 !
b1000 $
1#
b0 %
1"
#632
0"
#633
b1 %
1"
#634
0"
#635
b10 %
1"
#636
0"
#637
b11 %
1"
#638
0"
#639
0#
b0 %
1"
#640
0"
#641
b1 %
1"
#642
0"
#643
b10 %
1"
#644
0"
#645
b11 %
1"
#646
0"
#647
b1001 !
b1001 $
1#
b0 %
1"
#648
0"
#649
b1 %
1"
#650
0"
#651
b10 %
1"
#652
0"
#653
b11 %
1"
#654
0"
#655
0#
b0 %
1"
#656
0"
#657
b1 %
1"
#658
0"
#659
b10 %
1"
#660
0"
#661
b11 %
1"
#662
0"
#663
b1010 !
b1010 $
1#
b0 %
1"
#664
0"
#665
b1 %
1"
#666
0"
#667
b10 %
1"
#668
0"
#669
b11 %
1"
#670
0"
#671
0#
b0 %
1"
#672
0"
#673
b1 %
1"
#674
0"
#675
b10 %
1"
#676
0"
#677
b11 %
1"
#678
0"
#679
b1011 !
b1011 $
1#
b0 %
1"
#680
0"
#681
b1 %
1"
#682
0"
#683
b10 %
1"
#684
0"
#685
b11 %
1"
#686
0"
#687
0#
b0 %
1"
#688
0"
#689
b1 %
1"
#690
0"
#691
b10 %
1"
#692
0"
#693
b11 %
1"
#694
0"
#695
b1100 !
b1100 $
1#
b0 %
1"
#696
0"
#697
b1 %
1"
#698
0"
#699
b10 %
1"
#700
0"
#701
b11 %
1"
#702
0"
#703
0#
b0 %
1"
#704
0"
#705
b1 %
1"
#706
0"
#707
b10 %
1"
#708
0"
#709
b11 %
1"
#710
0"
#711
b1101 !
b1101 $
1#
b0 %
1"
#712
0"
#713
b1 %
1"
#714
0"
#715
b10 %
1"
#716
0"
#717
b11 %
1"
#718
0"
#719
0#
b0 %
1"
#720
0"
#721
b1 %
1"
#722
0"
#723
b10 %
1"
#724
0"
#725
b11 %
1"
#726
0"
#727
b1110 !
b1110 $
1#
b0 %
1"
#728
0"
#729
b1 %
1"
#730
0"
#731
b10 %
1"
#732
0"
#733
b11 %
1"
#734
0"
#735
0#
b0 %
1"
#736
0"
#737
b1 %
1"
#738
0"
#739
b10 %
1"
#740
0"
#741
b11 %
1"
#742
0"
#743
b1111 !
b1111 $
1#
b0 %
1"
#744
0"
#745
b1 %
1"
#746
0"
#747
b10 %
1"
#748
0"
#749
b11 %
1"
#750
0"
#751
0#
b0 %
1"
#752
0"
#753
b1 %
1"
#754
0"
#755
b10 %
1"
#756
0"
#757
b11 %
1"
#758
0"
#759
b0 !
b0 $
1#
b0 %
1"
#760
0"
#761
b1 %
1"
#762
0"
#763
b10 %
1"
#764
0"
#765
b11 %
1"
#766
0"
#767
0#
b0 %
1"
#768
0"
#769
b1 %
1"
#770
0"
#771
b10 %
1"
#772
0"
#773
b11 %
1"
#774
0"
#775
b1 !
b1 $
1#
b0 %
1"
#776
0"
#777
b1 %
1"
#778
0"
#779
b10 %
1"
#780
0"
#781
b11 %
1"
#782
0"
#783
0#
b0 %
1"
#784
0"
#785
b1 %
1"
#786
0"
#787
b10 %
1"
#788
0"
#789
b11 %
1"
#790
0"
#791
b10 !
b10 $
1#
b0 %
1"
#792
0"
#793
b1 %
1"
#794
0"
#795
b10 %
1"
#796
0"
#797
b11 %
1"
#798
0"
#799
0#
b0 %
1"
#800
0"
#801
b1 %
1"
#802
0"
#803
b10 %
1"
#804
0"
#805
b11 %
1"
#806
0"
#807
b11 !
b11 $
1#
b0 %
1"
#808
0"
#809
b1 %
1"
#810
0"
#811
b10 %
1"
#812
0"
#813
b11 %
1"
#814
0"
#815
0#
b0 %
1"
#816
0"
#817
b1 %
1"
#818
0"
#819
b10 %
1"
#820
0"
#821
b11 %
1"
#822
0"
#823
b100 !
b100 $
1#
b0 %
1"
#824
0"
#825
b1 %
1"
#826
0"
#827
b10 %
1"
#828
0"
#829
b11 %
1"
#830
0"
#831
0#
b0 %
1"
#832
0"
#833
b1 %
1"
#834
0"
#835
b10 %
1"
#836
0"
#837
b11 %
1"
#838
0"
#839
b101 !
b101 $
1#
b0 %
1"
#840
0"
#841
b1 %
1"
#842
0"
#843
b10 %
1"
#844
0"
#845
b11 %
1"
#846
0"
#847
0#
b0 %
1"
#848
0"
#849
b1 %
1"
#850
0"
#851
b10 %
1"
#852
0"
#853
b11 %
1"
#854
0"
#855
b110 !
b110 $
1#
b0 %
1"
#856
0"
#857
b1 %
1"
#858
0"
#859
b10 %
1"
#860
0"
#861
b11 %
1"
#862
0"
#863
0#
b0 %
1"
#864
0"
#865
b1 %
1"
#866
0"
#867
b10 %
1"
#868
0"
#869
b11 %
1"
#870
0"
#871
b111 !
b111 $
1#
b0 %
1"
#872
0"
#873
b1 %
1"
#874
0"
#875
b10 %
1"
#876
0"
#877
b11 %
1"
#878
0"
#879
0#
b0 %
1"
#880
0"
#881
b1 %
1"
#882
0"
#883
b10 %
1"
#884
0"
#885
b11 %
1"
#886
0"
#887
b1000 !
b1000 $
1#
b0 %
1"
#888
0"
#889
b1 %
1"
#890
0"
#891
b10 %
1"
#892
0"
#893
b11 %
1"
#894
0"
#895
0#
b0 %
1"
#896
0"
#897
b1 %
1"
#898
0"
#899
b10 %
1"
#900
0"
#901
b11 %
1"
#902
0"
#903
b1001 !
b1001 $
1#
b0 %
1"
#904
0"
#905
b1 %
1"
#906
0"
#907
b10 %
1"
#908
0"
#909
b11 %
1"
#910
0"
#911
0#
b0 %
1"
#912
0"
#913
b1 %
1"
#914
0"
#915
b10 %
1"
#916
0"
#917
b11 %
1"
#918
0"
#919
b1010 !
b1010 $
1#
b0 %
1"
#920
0"
#921
b1 %
1"
#922
0"
#923
b10 %
1"
#924
0"
#925
b11 %
1"
#926
0"
#927
0#
b0 %
1"
#928
0"
#929
b1 %
1"
#930
0"
#931
b10 %
1"
#932
0"
#933
b11 %
1"
#934
0"
#935
b1011 !
b1011 $
1#
b0 %
1"
#936
0"
#937
b1 %
1"
#938
0"
#939
b10 %
1"
#940
0"
#941
b11 %
1"
#942
0"
#943
0#
b0 %
1"
#944
0"
#945
b1 %
1"
#946
0"
#947
b10 %
1"
#948
0"
#949
b11 %
1"
#950
0"
#951
b1100 !
b1100 $
1#
b0 %
1"
#952
0"
#953
b1 %
1"
#954
0"
#955
b10 %
1"
#956
0"
#957
b11 %
1"
#958
0"
#959
0#
b0 %
1"
#960
0"
#961
b1 %
1"
#962
0"
#963
b10 %
1"
#964
0"
#965
b11 %
1"
#966
0"
#967
b1101 !
b1101 $
1#
b0 %
1"
#968
0"
#969
b1 %
1"
#970
0"
#971
b10 %
1"
#972
0"
#973
b11 %
1"
#974
0"
#975
0#
b0 %
1"
#976
0"
#977
b1 %
1"
#978
0"
#979
b10 %
1"
#980
0"
#981
b11 %
1"
#982
0"
#983
b1110 !
b1110 $
1#
b0 %
1"
#984
0"
#985
b1 %
1"
#986
0"
#987
b10 %
1"
#988
0"
#989
b11 %
1"
#990
0"
#991
0#
b0 %
1"
#992
0"
#993
b1 %
1"
#994
0"
#995
b10 %
1"
#996
0"
#997
b11 %
1"
#998
0"
#999
b1111 !
b1111 $
1#
b0 %
1"
